{"inmisaddon":51732,"adventurez":34499,"aged":16613,"libz":13194,"dungeonz":12028,"backslot":9820,"levelz":8956,"backslotaddon":7583,"dehydration":7299,"talkbubbles":6756,"voidz":6691,"jobsaddon":6446,"dragonloot":5887,"fleshz":5497,"nameplate":5403,"revive":5269,"partyaddon":5043,"additionz":4984,"medievalweapons":4842,"rpgdifficulty":4382,"reciperemover":4260,"tieredz":4252,"herdspanic":4081,"environmentz":3272,"patchoulibutton":3070,"earlystage":2607,"spoiledz":2566,"villagertradefix":2342,"eventmod":2340,"numismaticclaim":2188,"tooltiprareness":2092,"dualwielding":894,"villagerquests":413,"medievalmusic":251,"fireplacemode":70,"welcomescreen":17,"rewardz":20,"rpgz":3208,"travelerz":43,"total":260910}